demo_reader/__init__.py
demo_reader/__main__.py
demo_reader/multireader.py
demo_reader/util/__init__.py
demo_reader/util/writer.py
tsuyo_demo_reader-1.0.0.dist-info/METADATA
tsuyo_demo_reader-1.0.0.dist-info/WHEEL
tsuyo_demo_reader-1.0.0.dist-info/top_level.txt
tsuyo_demo_reader-1.0.0.dist-info/RECORD
