Metadata-Version: 2.1
Name: tsuyo-demo-reader
Version: 1.0.0
Summary: Tools for reading various file formats
Home-page: UNKNOWN
License: UNKNOWN
Platform: UNKNOWN
